stanfordnlp/__init__.py
stanfordnlp/_version.py
stanfordnlp/run_pipeline.py
stanfordnlp/models/__init__.py
stanfordnlp/models/identity_lemmatizer.py
stanfordnlp/models/lemmatizer.py
stanfordnlp/models/mwt_expander.py
stanfordnlp/models/parser.py
stanfordnlp/models/tagger.py
stanfordnlp/models/tokenizer.py
stanfordnlp/models/udpipe_wrapper.py
stanfordnlp/models/common/__init__.py
stanfordnlp/models/common/beam.py
stanfordnlp/models/common/biaffine.py
stanfordnlp/models/common/char_model.py
stanfordnlp/models/common/chuliu_edmonds.py
stanfordnlp/models/common/conll.py
stanfordnlp/models/common/constant.py
stanfordnlp/models/common/data.py
stanfordnlp/models/common/dropout.py
stanfordnlp/models/common/hlstm.py
stanfordnlp/models/common/loss.py
stanfordnlp/models/common/packed_lstm.py
stanfordnlp/models/common/pretrain.py
stanfordnlp/models/common/seq2seq_constant.py
stanfordnlp/models/common/seq2seq_model.py
stanfordnlp/models/common/seq2seq_modules.py
stanfordnlp/models/common/seq2seq_utils.py
stanfordnlp/models/common/trainer.py
stanfordnlp/models/common/utils.py
stanfordnlp/models/common/vocab.py
stanfordnlp/models/depparse/__init__.py
stanfordnlp/models/depparse/data.py
stanfordnlp/models/depparse/model.py
stanfordnlp/models/depparse/scorer.py
stanfordnlp/models/depparse/trainer.py
stanfordnlp/models/lemma/__init__.py
stanfordnlp/models/lemma/data.py
stanfordnlp/models/lemma/edit.py
stanfordnlp/models/lemma/scorer.py
stanfordnlp/models/lemma/trainer.py
stanfordnlp/models/lemma/vocab.py
stanfordnlp/models/mwt/__init__.py
stanfordnlp/models/mwt/data.py
stanfordnlp/models/mwt/scorer.py
stanfordnlp/models/mwt/trainer.py
stanfordnlp/models/mwt/vocab.py
stanfordnlp/models/pos/__init__.py
stanfordnlp/models/pos/build_xpos_vocab_factory.py
stanfordnlp/models/pos/data.py
stanfordnlp/models/pos/model.py
stanfordnlp/models/pos/scorer.py
stanfordnlp/models/pos/trainer.py
stanfordnlp/models/pos/vocab.py
stanfordnlp/models/pos/xpos_vocab_factory.py
stanfordnlp-0.2.0.dist-info/LICENSE
stanfordnlp-0.2.0.dist-info/METADATA
stanfordnlp-0.2.0.dist-info/WHEEL
stanfordnlp-0.2.0.dist-info/top_level.txt
stanfordnlp-0.2.0.dist-info/RECORD
