Metadata-Version: 2.1
Name: stanfordnlp
Version: 0.2.0
Summary: Official Stanford NLP Python Library
Home-page: https://github.com/stanfordnlp/stanfordnlp.git
Author: Stanford Natural Language Processing Group
Author-email: jebolton@stanford.edu
License: Apache License 2.0
Keywords: natural-language-processing nlp natural-language-understanding stanford-nlp
Platform: UNKNOWN
Classifier: Development Status :: 4 - Beta
Classifier: Intended Audience :: Developers
Classifier: Topic :: Scientific/Engineering :: Artificial Intelligence
Classifier: Programming Language :: Python :: 3.6
Classifier: Programming Language :: Python :: 3.7
Provides-Extra: test
Provides-Extra: dev
